metalnetes/log/__init__.py
metalnetes-1.0.16.dist-info/LICENSE
metalnetes-1.0.16.dist-info/METADATA
metalnetes-1.0.16.dist-info/WHEEL
metalnetes-1.0.16.dist-info/entry_points.txt
metalnetes-1.0.16.dist-info/top_level.txt
metalnetes-1.0.16.dist-info/RECORD
