Metadata-Version: 2.1
Name: metalnetes
Version: 1.0.16
Summary: Tools for managing multiple Kubernetes clusters on KVM (on 3 Centos 7 VMs) running on a bare metal Fedora 29 server (Ubuntu 18.04 was tested until Kubernetes v1.14)
Home-page: https://github.com/jay-johnson/metalnetes
Author: Jay Johnson
Author-email: jay.p.h.johnson@gmail.com
License: UNKNOWN
Platform: UNKNOWN
Classifier: Development Status :: 5 - Production/Stable
Classifier: Intended Audience :: Developers
Classifier: License :: OSI Approved :: Apache Software License
Classifier: Operating System :: OS Independent
Classifier: Programming Language :: Python :: 2.7
Classifier: Programming Language :: Python :: 3.6
Classifier: Programming Language :: Python :: Implementation :: PyPy
Classifier: Topic :: Software Development :: Libraries :: Python Modules
Requires-Dist: awscli
Requires-Dist: boto3
Requires-Dist: bs4
Requires-Dist: celery
Requires-Dist: celery[redis]
Requires-Dist: colorlog
Requires-Dist: coverage
Requires-Dist: flake8 (<=3.4.1)
Requires-Dist: future
Requires-Dist: mock
Requires-Dist: pep8 (>=1.7.1)
Requires-Dist: pycodestyle (<=2.3.1)
Requires-Dist: pylint
Requires-Dist: recommonmark
Requires-Dist: redis (>=3.2.0)
Requires-Dist: sphinx
Requires-Dist: sphinx-autobuild
Requires-Dist: sphinx-rtd-theme
Requires-Dist: tabulate
Requires-Dist: unittest2
Requires-Dist: urllib3 (<=1.23)
Requires-Dist: ujson
